soupstars/__init__.py
soupstars/api.py
soupstars/config.py
soupstars/decorators.py
soupstars/json.py
soupstars/loaders.py
soupstars/loggers.py
soupstars/parsers.py
soupstars/queues.py
soupstars/resources.py
soupstars/runners.py
soupstars/version.py
soupstars/workers.py
soupstars/writers.py
soupstars/cli/__init__.py
soupstars/cli/base.py
soupstars/cli/cloud.py
soupstars/cli/logs.py
soupstars/cli/printers.py
soupstars/examples/__init__.py
soupstars/examples/economist.py
soupstars/examples/nytimes.py
soupstars/examples/wsj.py
soupstars-2.11.25.dist-info/LICENSE
soupstars-2.11.25.dist-info/METADATA
soupstars-2.11.25.dist-info/WHEEL
soupstars-2.11.25.dist-info/entry_points.txt
soupstars-2.11.25.dist-info/top_level.txt
soupstars-2.11.25.dist-info/RECORD
