Metadata-Version: 2.1
Name: soupstars
Version: 2.11.25
Summary: Declarative web parsers
Home-page: https://soupstars.readthedocs.org
Author: Tom Waterman
Author-email: tjwaterman99@gmail.com
License: UNKNOWN
Keywords: scraping parsing beautifulsoup beautiful soup
Platform: UNKNOWN
Classifier: Development Status :: 3 - Alpha
Classifier: License :: OSI Approved :: MIT License
Classifier: Programming Language :: Python :: 3.7
Requires-Dist: beautifulsoup4 (==4.8.0)
Requires-Dist: requests (==2.22)
Requires-Dist: click (==7.0)
Requires-Dist: pygments (==2.4.2)
Requires-Dist: terminaltables (==3.1.0)
